{
  "changelogDate": "20220303210300",
  "dto": "no",
  "fields": [
    {
      "fieldName": "nombre",
      "fieldType": "String",
      "fieldValidateRules": ["required", "minlength", "maxlength"],
      "fieldValidateRulesMaxlength": "255",
      "fieldValidateRulesMinlength": "10"
    },
    {
      "fieldName": "apellidos",
      "fieldType": "String",
      "fieldValidateRules": ["required", "minlength", "maxlength"],
      "fieldValidateRulesMaxlength": "255",
      "fieldValidateRulesMinlength": "10"
    },
    {
      "fieldName": "dni",
      "fieldType": "String",
      "fieldValidateRules": ["required", "unique", "pattern"],
      "fieldValidateRulesPattern": "[0-9]{8}[TRWAGMYFPDXBNJZSQVHLCKE]"
    },
    {
      "fieldName": "direccion",
      "fieldType": "String",
      "fieldValidateRules": ["required", "minlength", "maxlength"],
      "fieldValidateRulesMaxlength": "255",
      "fieldValidateRulesMinlength": "10"
    },
    {
      "fieldName": "email",
      "fieldType": "String",
      "fieldValidateRules": ["required", "unique", "pattern"],
      "fieldValidateRulesPattern": "^[^@\\\\s]+@[^@\\\\s]+\\\\.[^@\\\\s]+$"
    },
    {
      "fieldName": "foto",
      "fieldType": "byte[]",
      "fieldTypeBlobContent": "image",
      "fieldValidateRules": ["required"]
    }
  ],
  "jpaMetamodelFiltering": true,
  "name": "Tripulante",
  "pagination": "pagination",
  "readOnly": false,
  "relationships": [
    {
      "otherEntityName": "vuelo",
      "otherEntityRelationshipName": "tripulacion",
      "ownerSide": false,
      "relationshipName": "vuelo",
      "relationshipType": "many-to-many"
    }
  ],
  "service": "serviceImpl"
}
